{
  "name": "2026-06-02",
  "category": "selection-control",
  "description": "2026-06-02 component (auto-generated metadata).",
  "interactionStates": [
    "default",
    "hover"
  ],
  "assets": {
    "variants": {
      "regular-inactive": {
        "default": "variants/regular-inactive/default.svg",
        "hover": "variants/regular-inactive/hover.svg"
      },
      "regular-active": {
        "default": "variants/regular-active/default.svg",
        "hover": "variants/regular-active/hover.svg"
      }
    }
  },
  "tokens": {
    "modes": {
      "light": {
        "foreground": "mapped/light.foreground.foreground"
      },
      "dark": {
        "foreground": "mapped/dark.foreground.foreground"
      }
    }
  },
  "notes": [
    "Auto-generated by designs/scripts/normalize_design_exports.py from variants/* exports.",
    "Edit description/notes as needed; rerunning the script will not overwrite this file."
  ]
}
