{
  "name": "menu-bottom-navigation",
  "category": "menu",
  "description": "Bottom navigation menu items.",
  "interactionStates": [
    "default",
    "hover",
    "focus"
  ],
  "assets": {
    "variants": {
      "default-default": {
        "default": "variants/default-default/default.svg"
      },
      "bottom-nav-selected": {
        "focus": "variants/bottom-nav-selected/focus.svg",
        "default": "variants/bottom-nav-selected/default.svg",
        "hover": "variants/bottom-nav-selected/hover.svg",
        "pressed 2": "variants/bottom-nav-selected/pressed 2.svg",
        "pressed": "variants/bottom-nav-selected/pressed.svg"
      },
      "bottom-nav-unselected": {
        "focus": "variants/bottom-nav-unselected/focus.svg",
        "default": "variants/bottom-nav-unselected/default.svg",
        "hover": "variants/bottom-nav-unselected/hover.svg",
        "pressed 2": "variants/bottom-nav-unselected/pressed 2.svg",
        "pressed": "variants/bottom-nav-unselected/pressed.svg"
      }
    },
    "overview": "overview.png"
  },
  "tokens": {
    "radius": "alias.radius.regular",
    "modes": {
      "light": {
        "foreground": "mapped/light.foreground.foreground"
      },
      "dark": {
        "foreground": "mapped/dark.foreground.foreground"
      }
    }
  },
  "notes": [
    "Figma exports `Pressed` are stored as `focus.svg` for consistency."
  ]
}
